Metadata-Version: 2.1
Name: DEL.py
Version: 1.0.1
Summary: API wrapper for discordextremelist
Home-page: https://github.com/discordextremelist/del.py
Author: Moksej
Author-email: moksej@gmail.com
License: MIT
Download-URL: https://github.com/discordextremelist/del.py.git
Platform: UNKNOWN
Classifier: License :: OSI Approved :: MIT License
Classifier: Programming Language :: Python :: 3
